[
  {
    "name": "BTC",
    "maxLeverage": 40,
    "mark": 66286.0,
    "prevDay": 67288.0,
    "chg24h": -1.49,
    "funding8h": 0.0013,
    "annualizedFunding": 1.37,
    "oi": 18850.0581,
    "oiUsd": 1249494951,
    "vol24h": 3012852408,
    "premium": -0.0392
  },
  {
    "name": "ETH",
    "maxLeverage": 25,
    "mark": 1942.2,
    "prevDay": 1946.3,
    "chg24h": -0.21,
    "funding8h": 0.0013,
    "annualizedFunding": 1.37,
    "oi": 497168.6274,
    "oiUsd": 965600908,
    "vol24h": 880103135,
    "premium": -0.0376
  },
  {
    "name": "ATOM",
    "maxLeverage": 5,
    "mark": 1.9614,
    "prevDay": 1.9338,
    "chg24h": 1.43,
    "funding8h": 0.0013,
    "annualizedFunding": 1.37,
    "oi": 1426088.5,
    "oiUsd": 2797130,
    "vol24h": 1201837,
    "premium": -0.0102
  },
  {
    "name": "MATIC",
    "maxLeverage": 20,
    "mark": 0.37621,
    "prevDay": 0.37621,
    "chg24h": 0.0,
    "funding8h": 0.0,
    "annualizedFunding": 0.0,
    "oi": 0.0,
    "oiUsd": 0,
    "vol24h": 0,
    "premium": 0.0
  },
  {
    "name": "DYDX",
    "maxLeverage": 5,
    "mark": 0.10283,
    "prevDay": 0.10006,
    "chg24h": 2.77,
    "funding8h": 0.0013,
    "annualizedFunding": 1.37,
    "oi": 15587773.4,
    "oiUsd": 1602891,
    "vol24h": 275652,
    "premium": 0.0
  },
  {
    "name": "SOL",
    "maxLeverage": 20,
    "mark": 78.065,
    "prevDay": 79.334,
    "chg24h": -1.6,
    "funding8h": 0.0005,
    "annualizedFunding": 0.52,
    "oi": 3441277.18,
    "oiUsd": 268643303,
    "vol24h": 292984988,
    "premium": -0.0575
  },
  {
    "name": "AVAX",
    "maxLeverage": 10,
    "mark": 8.8635,
    "prevDay": 8.65,
    "chg24h": 2.47,
    "funding8h": 0.0013,
    "annualizedFunding": 1.37,
    "oi": 3379617.22,
    "oiUsd": 29955237,
    "vol24h": 3995055,
    "premium": 0.0
  },
  {
    "name": "BNB",
    "maxLeverage": 10,
    "mark": 613.09,
    "prevDay": 607.89,
    "chg24h": 0.86,
    "funding8h": 0.001,
    "annualizedFunding": 1.12,
    "oi": 40703.81,
    "oiUsd": 24955099,
    "vol24h": 7874672,
    "premium": -0.0453
  },
  {
    "name": "APE",
    "maxLeverage": 5,
    "mark": 0.12755,
    "prevDay": 0.12286,
    "chg24h": 3.82,
    "funding8h": 0.0013,
    "annualizedFunding": 1.37,
    "oi": 6850572.6,
    "oiUsd": 873791,
    "vol24h": 380242,
    "premium": 0.0
  },
  {
    "name": "OP",
    "maxLeverage": 10,
    "mark": 0.1823,
    "prevDay": 0.17771,
    "chg24h": 2.58,
    "funding8h": -0.0021,
    "annualizedFunding": -2.3,
    "oi": 18825691.2,
    "oiUsd": 3431924,
    "vol24h": 1392107,
    "premium": -0.0548
  },
  {
    "name": "LTC",
    "maxLeverage": 10,
    "mark": 52.935,
    "prevDay": 52.195,
    "chg24h": 1.42,
    "funding8h": 0.0013,
    "annualizedFunding": 1.37,
    "oi": 264766.58,
    "oiUsd": 14015419,
    "vol24h": 1808431,
    "premium": -0.0491
  },
  {
    "name": "ARB",
    "maxLeverage": 10,
    "mark": 0.11096,
    "prevDay": 0.10834,
    "chg24h": 2.42,
    "funding8h": 0.0013,
    "annualizedFunding": 1.37,
    "oi": 28136326.0,
    "oiUsd": 3122007,
    "vol24h": 2820015,
    "premium": -0.063
  },
  {
    "name": "DOGE",
    "maxLeverage": 10,
    "mark": 0.092815,
    "prevDay": 0.090934,
    "chg24h": 2.07,
    "funding8h": 0.0004,
    "annualizedFunding": 0.42,
    "oi": 182457598.0,
    "oiUsd": 16934802,
    "vol24h": 10575317,
    "premium": -0.0517
  },
  {
    "name": "INJ",
    "maxLeverage": 10,
    "mark": 3.0341,
    "prevDay": 3.0125,
    "chg24h": 0.72,
    "funding8h": 0.0013,
    "annualizedFunding": 1.37,
    "oi": 713117.4,
    "oiUsd": 2163670,
    "vol24h": 597934,
    "premium": -0.0115
  },
  {
    "name": "SUI",
    "maxLeverage": 10,
    "mark": 0.92148,
    "prevDay": 0.89316,
    "chg24h": 3.17,
    "funding8h": 0.0013,
    "annualizedFunding": 1.37,
    "oi": 15674086.6,
    "oiUsd": 14443357,
    "vol24h": 18449868,
    "premium": -0.0054
  },
  {
    "name": "kPEPE",
    "maxLeverage": 10,
    "mark": 0.003704,
    "prevDay": 0.003546,
    "chg24h": 4.46,
    "funding8h": 0.0013,
    "annualizedFunding": 1.37,
    "oi": 2655459564.0,
    "oiUsd": 9835822,
    "vol24h": 5513676,
    "premium": -0.027
  },
  {
    "name": "CRV",
    "maxLeverage": 10,
    "mark": 0.23705,
    "prevDay": 0.23176,
    "chg24h": 2.28,
    "funding8h": 0.0013,
    "annualizedFunding": 1.37,
    "oi": 25655464.6,
    "oiUsd": 6081628,
    "vol24h": 5301105,
    "premium": -0.0295
  },
  {
    "name": "LDO",
    "maxLeverage": 10,
    "mark": 0.3364,
    "prevDay": 0.32911,
    "chg24h": 2.22,
    "funding8h": 0.0013,
    "annualizedFunding": 1.37,
    "oi": 13047276.8,
    "oiUsd": 4389104,
    "vol24h": 865175,
    "premium": -0.0208
  },
  {
    "name": "LINK",
    "maxLeverage": 10,
    "mark": 8.3885,
    "prevDay": 8.3256,
    "chg24h": 0.76,
    "funding8h": 0.0013,
    "annualizedFunding": 1.37,
    "oi": 2165033.2,
    "oiUsd": 18161381,
    "vol24h": 5110901,
    "premium": -0.0015
  },
  {
    "name": "STX",
    "maxLeverage": 5,
    "mark": 0.26421,
    "prevDay": 0.25532,
    "chg24h": 3.48,
    "funding8h": 0.0013,
    "annualizedFunding": 1.37,
    "oi": 2972419.2,
    "oiUsd": 785343,
    "vol24h": 590367,
    "premium": -0.034
  },
  {
    "name": "RNDR",
    "maxLeverage": 20,
    "mark": 6.8952,
    "prevDay": 6.8946,
    "chg24h": 0.01,
    "funding8h": 0.0,
    "annualizedFunding": 0.0,
    "oi": 0.0,
    "oiUsd": 0,
    "vol24h": 0,
    "premium": 0.0
  },
  {
    "name": "CFX",
    "maxLeverage": 5,
    "mark": 0.048571,
    "prevDay": 0.045075,
    "chg24h": 7.76,
    "funding8h": 0.0013,
    "annualizedFunding": 1.37,
    "oi": 13522188.0,
    "oiUsd": 656786,
    "vol24h": 583834,
    "premium": 0.0
  },
  {
    "name": "FTM",
    "maxLeverage": 10,
    "mark": 0.71688,
    "prevDay": 0.73,
    "chg24h": -1.8,
    "funding8h": 0.0,
    "annualizedFunding": 0.0,
    "oi": 0.0,
    "oiUsd": 0,
    "vol24h": 0,
    "premium": 0.0
  },
  {
    "name": "GMX",
    "maxLeverage": 3,
    "mark": 6.029,
    "prevDay": 5.9242,
    "chg24h": 1.77,
    "funding8h": -0.0,
    "annualizedFunding": -0.01,
    "oi": 52215.54,
    "oiUsd": 314807,
    "vol24h": 155959,
    "premium": -0.0812
  },
  {
    "name": "SNX",
    "maxLeverage": 3,
    "mark": 0.28735,
    "prevDay": 0.27789,
    "chg24h": 3.4,
    "funding8h": 0.0013,
    "annualizedFunding": 1.37,
    "oi": 1504799.8,
    "oiUsd": 432404,
    "vol24h": 313164,
    "premium": 0.0
  },
  {
    "name": "XRP",
    "maxLeverage": 20,
    "mark": 1.3647,
    "prevDay": 1.3669,
    "chg24h": -0.16,
    "funding8h": -0.0005,
    "annualizedFunding": -0.59,
    "oi": 65059700.0,
    "oiUsd": 88786973,
    "vol24h": 106180854,
    "premium": -0.0659
  },
  {
    "name": "BCH",
    "maxLeverage": 10,
    "mark": 500.85,
    "prevDay": 516.45,
    "chg24h": -3.02,
    "funding8h": 0.0011,
    "annualizedFunding": 1.2,
    "oi": 18541.358,
    "oiUsd": 9286439,
    "vol24h": 2538879,
    "premium": -0.0369
  },
  {
    "name": "APT",
    "maxLeverage": 10,
    "mark": 0.9202,
    "prevDay": 0.9187,
    "chg24h": 0.16,
    "funding8h": -0.0073,
    "annualizedFunding": -7.99,
    "oi": 6703855.6,
    "oiUsd": 6168888,
    "vol24h": 1954336,
    "premium": -0.0977
  },
  {
    "name": "AAVE",
    "maxLeverage": 10,
    "mark": 112.86,
    "prevDay": 107.86,
    "chg24h": 4.64,
    "funding8h": 0.0013,
    "annualizedFunding": 1.37,
    "oi": 209183.8,
    "oiUsd": 23608484,
    "vol24h": 12790007,
    "premium": -0.0452
  },
  {
    "name": "COMP",
    "maxLeverage": 5,
    "mark": 16.059,
    "prevDay": 15.917,
    "chg24h": 0.89,
    "funding8h": -0.0041,
    "annualizedFunding": -4.47,
    "oi": 35324.06,
    "oiUsd": 567269,
    "vol24h": 113379,
    "premium": -0.0466
  },
  {
    "name": "MKR",
    "maxLeverage": 10,
    "mark": 1831.5,
    "prevDay": 1843.8,
    "chg24h": -0.67,
    "funding8h": 0.0,
    "annualizedFunding": 0.0,
    "oi": 0.0,
    "oiUsd": 0,
    "vol24h": 0,
    "premium": 0.0
  },
  {
    "name": "WLD",
    "maxLeverage": 10,
    "mark": 0.38189,
    "prevDay": 0.36889,
    "chg24h": 3.52,
    "funding8h": 0.0013,
    "annualizedFunding": 1.37,
    "oi": 21492813.8,
    "oiUsd": 8207891,
    "vol24h": 3099378,
    "premium": 0.0
  },
  {
    "name": "FXS",
    "maxLeverage": 5,
    "mark": 0.65538,
    "prevDay": 0.65598,
    "chg24h": -0.09,
    "funding8h": 0.0,
    "annualizedFunding": 0.0,
    "oi": 0.0,
    "oiUsd": 0,
    "vol24h": 0,
    "premium": 0.0
  },
  {
    "name": "HPOS",
    "maxLeverage": 3,
    "mark": 0.041873,
    "prevDay": 0.041845,
    "chg24h": 0.07,
    "funding8h": 0.0,
    "annualizedFunding": 0.0,
    "oi": 0.0,
    "oiUsd": 0,
    "vol24h": 0,
    "premium": 0.0
  },
  {
    "name": "RLB",
    "maxLeverage": 3,
    "mark": 0.071,
    "prevDay": 0.071,
    "chg24h": 0.0,
    "funding8h": 0.0,
    "annualizedFunding": 0.0,
    "oi": 0.0,
    "oiUsd": 0,
    "vol24h": 0,
    "premium": 0.0
  },
  {
    "name": "UNIBOT",
    "maxLeverage": 3,
    "mark": 7.636,
    "prevDay": 7.636,
    "chg24h": 0.0,
    "funding8h": 0.0,
    "annualizedFunding": 0.0,
    "oi": 0.0,
    "oiUsd": 0,
    "vol24h": 0,
    "premium": 0.0
  },
  {
    "name": "YGG",
    "maxLeverage": 3,
    "mark": 0.041045,
    "prevDay": 0.039744,
    "chg24h": 3.27,
    "funding8h": -0.0022,
    "annualizedFunding": -2.46,
    "oi": 5166674.0,
    "oiUsd": 212066,
    "vol24h": 239522,
    "premium": -0.09
  },
  {
    "name": "TRX",
    "maxLeverage": 10,
    "mark": 0.27992,
    "prevDay": 0.27731,
    "chg24h": 0.94,
    "funding8h": 0.0013,
    "annualizedFunding": 1.37,
    "oi": 26179080.0,
    "oiUsd": 7328048,
    "vol24h": 1082875,
    "premium": -0.02
  },
  {
    "name": "kSHIB",
    "maxLeverage": 10,
    "mark": 0.006027,
    "prevDay": 0.005894,
    "chg24h": 2.26,
    "funding8h": 0.0002,
    "annualizedFunding": 0.25,
    "oi": 359605928.0,
    "oiUsd": 2167345,
    "vol24h": 1247676,
    "premium": 0.0
  },
  {
    "name": "UNI",
    "maxLeverage": 10,
    "mark": 3.229,
    "prevDay": 3.4451,
    "chg24h": -6.27,
    "funding8h": 0.0013,
    "annualizedFunding": 1.37,
    "oi": 5646883.0,
    "oiUsd": 18233785,
    "vol24h": 26797908,
    "premium": -0.0189
  },
  {
    "name": "SEI",
    "maxLeverage": 10,
    "mark": 0.074305,
    "prevDay": 0.070637,
    "chg24h": 5.19,
    "funding8h": -0.0036,
    "annualizedFunding": -3.97,
    "oi": 30049234.0,
    "oiUsd": 2232808,
    "vol24h": 1528298,
    "premium": -0.0524
  },
  {
    "name": "RUNE",
    "maxLeverage": 5,
    "mark": 0.39023,
    "prevDay": 0.38781,
    "chg24h": 0.62,
    "funding8h": -0.0012,
    "annualizedFunding": -1.34,
    "oi": 2352834.2,
    "oiUsd": 918146,
    "vol24h": 383125,
    "premium": -0.0742
  },
  {
    "name": "OX",
    "maxLeverage": 3,
    "mark": 0.007459,
    "prevDay": 0.007459,
    "chg24h": 0.0,
    "funding8h": 0.0,
    "annualizedFunding": 0.0,
    "oi": 0.0,
    "oiUsd": 0,
    "vol24h": 0,
    "premium": 0.0
  },
  {
    "name": "FRIEND",
    "maxLeverage": 3,
    "mark": 4.72,
    "prevDay": 4.72,
    "chg24h": 0.0,
    "funding8h": 0.0,
    "annualizedFunding": 0.0,
    "oi": 0.0,
    "oiUsd": 0,
    "vol24h": 0,
    "premium": 0.0
  },
  {
    "name": "SHIA",
    "maxLeverage": 3,
    "mark": 0.000621,
    "prevDay": 0.000604,
    "chg24h": 2.81,
    "funding8h": 0.0,
    "annualizedFunding": 0.0,
    "oi": 0.0,
    "oiUsd": 0,
    "vol24h": 0,
    "premium": 0.0
  },
  {
    "name": "CYBER",
    "maxLeverage": 3,
    "mark": 1.0415,
    "prevDay": 1.0454,
    "chg24h": -0.37,
    "funding8h": 0.0,
    "annualizedFunding": 0.0,
    "oi": 0.0,
    "oiUsd": 0,
    "vol24h": 0,
    "premium": 0.0
  },
  {
    "name": "ZRO",
    "maxLeverage": 5,
    "mark": 1.9557,
    "prevDay": 2.1276,
    "chg24h": -8.08,
    "funding8h": 0.0013,
    "annualizedFunding": 1.37,
    "oi": 26337144.8,
    "oiUsd": 51507554,
    "vol24h": 47125121,
    "premium": 0.0
  },
  {
    "name": "BLZ",
    "maxLeverage": 5,
    "mark": 0.070043,
    "prevDay": 0.070239,
    "chg24h": -0.28,
    "funding8h": 0.0,
    "annualizedFunding": 0.0,
    "oi": 0.0,
    "oiUsd": 0,
    "vol24h": 0,
    "premium": 0.0
  },
  {
    "name": "DOT",
    "maxLeverage": 10,
    "mark": 1.2795,
    "prevDay": 1.2549,
    "chg24h": 1.96,
    "funding8h": 0.0013,
    "annualizedFunding": 1.37,
    "oi": 3120845.6,
    "oiUsd": 3993122,
    "vol24h": 799544,
    "premium": -0.0305
  },
  {
    "name": "BANANA",
    "maxLeverage": 3,
    "mark": 4.551,
    "prevDay": 4.4442,
    "chg24h": 2.4,
    "funding8h": -0.0057,
    "annualizedFunding": -6.24,
    "oi": 51075.8,
    "oiUsd": 232446,
    "vol24h": 88281,
    "premium": -0.145
  },
  {
    "name": "TRB",
    "maxLeverage": 3,
    "mark": 14.368,
    "prevDay": 13.958,
    "chg24h": 2.94,
    "funding8h": 0.0013,
    "annualizedFunding": 1.37,
    "oi": 34091.4,
    "oiUsd": 489825,
    "vol24h": 81647,
    "premium": -0.007
  },
  {
    "name": "FTT",
    "maxLeverage": 3,
    "mark": 0.33747,
    "prevDay": 0.33276,
    "chg24h": 1.42,
    "funding8h": 0.0013,
    "annualizedFunding": 1.37,
    "oi": 546177.2,
    "oiUsd": 184318,
    "vol24h": 31262,
    "premium": 0.0
  },
  {
    "name": "LOOM",
    "maxLeverage": 10,
    "mark": 0.071161,
    "prevDay": 0.07116,
    "chg24h": 0.0,
    "funding8h": 0.0,
    "annualizedFunding": 0.0,
    "oi": 0.0,
    "oiUsd": 0,
    "vol24h": 0,
    "premium": 0.0
  },
  {
    "name": "OGN",
    "maxLeverage": 3,
    "mark": 0.055683,
    "prevDay": 0.0558,
    "chg24h": -0.21,
    "funding8h": 0.0,
    "annualizedFunding": 0.0,
    "oi": 0.0,
    "oiUsd": 0,
    "vol24h": 0,
    "premium": 0.0
  },
  {
    "name": "RDNT",
    "maxLeverage": 5,
    "mark": 0.018328,
    "prevDay": 0.018338,
    "chg24h": -0.05,
    "funding8h": 0.0,
    "annualizedFunding": 0.0,
    "oi": 0.0,
    "oiUsd": 0,
    "vol24h": 0,
    "premium": 0.0
  },
  {
    "name": "ARK",
    "maxLeverage": 3,
    "mark": 0.1898,
    "prevDay": 0.18709,
    "chg24h": 1.45,
    "funding8h": -0.0208,
    "annualizedFunding": -22.73,
    "oi": 1253218.0,
    "oiUsd": 237861,
    "vol24h": 88678,
    "premium": -0.1498
  },
  {
    "name": "BNT",
    "maxLeverage": 3,
    "mark": 0.38287,
    "prevDay": 0.38457,
    "chg24h": -0.44,
    "funding8h": 0.0,
    "annualizedFunding": 0.0,
    "oi": 0.0,
    "oiUsd": 0,
    "vol24h": 0,
    "premium": 0.0
  },
  {
    "name": "CANTO",
    "maxLeverage": 5,
    "mark": 0.066,
    "prevDay": 0.066,
    "chg24h": 0.0,
    "funding8h": 0.0,
    "annualizedFunding": 0.0,
    "oi": 0.0,
    "oiUsd": 0,
    "vol24h": 0,
    "premium": 0.0
  },
  {
    "name": "REQ",
    "maxLeverage": 3,
    "mark": 0.15473,
    "prevDay": 0.15473,
    "chg24h": 0.0,
    "funding8h": 0.0,
    "annualizedFunding": 0.0,
    "oi": 0.0,
    "oiUsd": 0,
    "vol24h": 0,
    "premium": 0.0
  },
  {
    "name": "BIGTIME",
    "maxLeverage": 3,
    "mark": 0.015103,
    "prevDay": 0.014331,
    "chg24h": 5.39,
    "funding8h": -0.0095,
    "annualizedFunding": -10.38,
    "oi": 14800898.0,
    "oiUsd": 223538,
    "vol24h": 161089,
    "premium": -0.1189
  },
  {
    "name": "KAS",
    "maxLeverage": 3,
    "mark": 0.031443,
    "prevDay": 0.031565,
    "chg24h": -0.39,
    "funding8h": -0.0045,
    "annualizedFunding": -4.93,
    "oi": 22213926.0,
    "oiUsd": 698472,
    "vol24h": 140795,
    "premium": -0.0318
  },
  {
    "name": "ORBS",
    "maxLeverage": 3,
    "mark": 0.01939,
    "prevDay": 0.01939,
    "chg24h": 0.0,
    "funding8h": 0.0,
    "annualizedFunding": 0.0,
    "oi": 0.0,
    "oiUsd": 0,
    "vol24h": 0,
    "premium": 0.0
  },
  {
    "name": "BLUR",
    "maxLeverage": 3,
    "mark": 0.0208,
    "prevDay": 0.019751,
    "chg24h": 5.31,
    "funding8h": 0.0013,
    "annualizedFunding": 1.37,
    "oi": 34801406.0,
    "oiUsd": 723869,
    "vol24h": 471981,
    "premium": 0.0
  },
  {
    "name": "TIA",
    "maxLeverage": 10,
    "mark": 0.32083,
    "prevDay": 0.30645,
    "chg24h": 4.69,
    "funding8h": -0.0013,
    "annualizedFunding": -1.43,
    "oi": 9031662.8,
    "oiUsd": 2897628,
    "vol24h": 960982,
    "premium": -0.0529
  },
  {
    "name": "BSV",
    "maxLeverage": 3,
    "mark": 14.798,
    "prevDay": 13.932,
    "chg24h": 6.22,
    "funding8h": 0.0013,
    "annualizedFunding": 1.37,
    "oi": 84957.28,
    "oiUsd": 1257198,
    "vol24h": 377814,
    "premium": -0.0755
  },
  {
    "name": "ADA",
    "maxLeverage": 10,
    "mark": 0.26253,
    "prevDay": 0.25589,
    "chg24h": 2.59,
    "funding8h": -0.0001,
    "annualizedFunding": -0.13,
    "oi": 51685188.0,
    "oiUsd": 13568912,
    "vol24h": 2441319,
    "premium": -0.0369
  },
  {
    "name": "TON",
    "maxLeverage": 10,
    "mark": 1.3926,
    "prevDay": 1.3122,
    "chg24h": 6.13,
    "funding8h": 0.0013,
    "annualizedFunding": 1.37,
    "oi": 5532911.6,
    "oiUsd": 7705133,
    "vol24h": 879400,
    "premium": 0.0
  },
  {
    "name": "MINA",
    "maxLeverage": 3,
    "mark": 0.067074,
    "prevDay": 0.065918,
    "chg24h": 1.75,
    "funding8h": 0.0006,
    "annualizedFunding": 0.71,
    "oi": 5979830.0,
    "oiUsd": 401091,
    "vol24h": 244320,
    "premium": -0.061
  },
  {
    "name": "POLYX",
    "maxLeverage": 3,
    "mark": 0.043395,
    "prevDay": 0.0426,
    "chg24h": 1.87,
    "funding8h": 0.0013,
    "annualizedFunding": 1.37,
    "oi": 6225328.0,
    "oiUsd": 270148,
    "vol24h": 46758,
    "premium": -0.0023
  },
  {
    "name": "GAS",
    "maxLeverage": 3,
    "mark": 1.5965,
    "prevDay": 1.5486,
    "chg24h": 3.09,
    "funding8h": 0.0013,
    "annualizedFunding": 1.37,
    "oi": 180406.2,
    "oiUsd": 288018,
    "vol24h": 190336,
    "premium": -0.0744
  },
  {
    "name": "PENDLE",
    "maxLeverage": 5,
    "mark": 1.1409,
    "prevDay": 1.1012,
    "chg24h": 3.61,
    "funding8h": -0.0003,
    "annualizedFunding": -0.3,
    "oi": 3595840.0,
    "oiUsd": 4102494,
    "vol24h": 723065,
    "premium": -0.039
  },
  {
    "name": "STG",
    "maxLeverage": 3,
    "mark": 0.15387,
    "prevDay": 0.1537,
    "chg24h": 0.11,
    "funding8h": 0.0,
    "annualizedFunding": 0.0,
    "oi": 0.0,
    "oiUsd": 0,
    "vol24h": 0,
    "premium": 0.0
  },
  {
    "name": "FET",
    "maxLeverage": 5,
    "mark": 0.15788,
    "prevDay": 0.15404,
    "chg24h": 2.49,
    "funding8h": 0.0013,
    "annualizedFunding": 1.37,
    "oi": 7790668.0,
    "oiUsd": 1229991,
    "vol24h": 459035,
    "premium": 0.0
  },
  {
    "name": "STRAX",
    "maxLeverage": 10,
    "mark": 1.5829,
    "prevDay": 1.5848,
    "chg24h": -0.12,
    "funding8h": 0.0,
    "annualizedFunding": 0.0,
    "oi": 0.0,
    "oiUsd": 0,
    "vol24h": 0,
    "premium": 0.0
  },
  {
    "name": "NEAR",
    "maxLeverage": 10,
    "mark": 0.9585,
    "prevDay": 0.95967,
    "chg24h": -0.12,
    "funding8h": 0.001,
    "annualizedFunding": 1.14,
    "oi": 5123520.0,
    "oiUsd": 4910894,
    "vol24h": 1581692,
    "premium": -0.0396
  },
  {
    "name": "MEME",
    "maxLeverage": 3,
    "mark": 0.000693,
    "prevDay": 0.000671,
    "chg24h": 3.28,
    "funding8h": -0.0078,
    "annualizedFunding": -8.54,
    "oi": 791646390.0,
    "oiUsd": 548611,
    "vol24h": 262864,
    "premium": -0.1441
  },
  {
    "name": "ORDI",
    "maxLeverage": 3,
    "mark": 2.7855,
    "prevDay": 2.7018,
    "chg24h": 3.1,
    "funding8h": 0.0004,
    "annualizedFunding": 0.39,
    "oi": 69337.12,
    "oiUsd": 193139,
    "vol24h": 100957,
    "premium": -0.061
  },
  {
    "name": "BADGER",
    "maxLeverage": 5,
    "mark": 0.88823,
    "prevDay": 0.89235,
    "chg24h": -0.46,
    "funding8h": 0.0,
    "annualizedFunding": 0.0,
    "oi": 0.0,
    "oiUsd": 0,
    "vol24h": 0,
    "premium": 0.0
  },
  {
    "name": "NEO",
    "maxLeverage": 5,
    "mark": 2.7079,
    "prevDay": 2.6554,
    "chg24h": 1.98,
    "funding8h": 0.0013,
    "annualizedFunding": 1.37,
    "oi": 112735.28,
    "oiUsd": 305276,
    "vol24h": 157616,
    "premium": -0.0111
  },
  {
    "name": "ZEN",
    "maxLeverage": 5,
    "mark": 5.9214,
    "prevDay": 5.7739,
    "chg24h": 2.55,
    "funding8h": 0.0013,
    "annualizedFunding": 1.37,
    "oi": 123632.76,
    "oiUsd": 732079,
    "vol24h": 516133,
    "premium": 0.0
  },
  {
    "name": "FIL",
    "maxLeverage": 5,
    "mark": 0.90914,
    "prevDay": 0.88226,
    "chg24h": 3.05,
    "funding8h": -0.0005,
    "annualizedFunding": -0.53,
    "oi": 2071229.0,
    "oiUsd": 1883037,
    "vol24h": 362866,
    "premium": 0.0
  },
  {
    "name": "PYTH",
    "maxLeverage": 5,
    "mark": 0.04668,
    "prevDay": 0.043788,
    "chg24h": 6.6,
    "funding8h": -0.0044,
    "annualizedFunding": -4.77,
    "oi": 15344728.0,
    "oiUsd": 716292,
    "vol24h": 739853,
    "premium": -0.0834
  },
  {
    "name": "SUSHI",
    "maxLeverage": 3,
    "mark": 0.19984,
    "prevDay": 0.19826,
    "chg24h": 0.8,
    "funding8h": 0.0,
    "annualizedFunding": 0.02,
    "oi": 1666247.8,
    "oiUsd": 332983,
    "vol24h": 260722,
    "premium": -0.04
  },
  {
    "name": "ILV",
    "maxLeverage": 3,
    "mark": 12.118,
    "prevDay": 12.128,
    "chg24h": -0.08,
    "funding8h": 0.0,
    "annualizedFunding": 0.0,
    "oi": 0.0,
    "oiUsd": 0,
    "vol24h": 0,
    "premium": 0.0
  },
  {
    "name": "IMX",
    "maxLeverage": 5,
    "mark": 0.1621,
    "prevDay": 0.15024,
    "chg24h": 7.89,
    "funding8h": 0.0013,
    "annualizedFunding": 1.37,
    "oi": 7640894.2,
    "oiUsd": 1238589,
    "vol24h": 362179,
    "premium": 0.0
  },
  {
    "name": "kBONK",
    "maxLeverage": 10,
    "mark": 0.006063,
    "prevDay": 0.00586,
    "chg24h": 3.46,
    "funding8h": 0.0005,
    "annualizedFunding": 0.59,
    "oi": 643504182.0,
    "oiUsd": 3901566,
    "vol24h": 2698137,
    "premium": -0.0165
  },
  {
    "name": "GMT",
    "maxLeverage": 3,
    "mark": 0.012387,
    "prevDay": 0.011947,
    "chg24h": 3.68,
    "funding8h": 0.0013,
    "annualizedFunding": 1.37,
    "oi": 28655872.0,
    "oiUsd": 354960,
    "vol24h": 94394,
    "premium": 0.0
  },
  {
    "name": "SUPER",
    "maxLeverage": 3,
    "mark": 0.12319,
    "prevDay": 0.12203,
    "chg24h": 0.95,
    "funding8h": -0.0037,
    "annualizedFunding": -4.02,
    "oi": 2980154.0,
    "oiUsd": 367125,
    "vol24h": 107341,
    "premium": 0.0
  },
  {
    "name": "USTC",
    "maxLeverage": 3,
    "mark": 0.004805,
    "prevDay": 0.004858,
    "chg24h": -1.09,
    "funding8h": 0.0013,
    "annualizedFunding": 1.37,
    "oi": 39816668.0,
    "oiUsd": 191319,
    "vol24h": 45025,
    "premium": -0.0208
  },
  {
    "name": "NFTI",
    "maxLeverage": 3,
    "mark": 6.5609,
    "prevDay": 6.6683,
    "chg24h": -1.61,
    "funding8h": 0.0,
    "annualizedFunding": 0.0,
    "oi": 0.0,
    "oiUsd": 0,
    "vol24h": 0,
    "premium": 0.0
  },
  {
    "name": "JUP",
    "maxLeverage": 10,
    "mark": 0.13786,
    "prevDay": 0.13638,
    "chg24h": 1.09,
    "funding8h": 0.0013,
    "annualizedFunding": 1.37,
    "oi": 27229020.0,
    "oiUsd": 3753793,
    "vol24h": 2090875,
    "premium": -0.0043
  },
  {
    "name": "kLUNC",
    "maxLeverage": 3,
    "mark": 0.03318,
    "prevDay": 0.033932,
    "chg24h": -2.22,
    "funding8h": -0.0078,
    "annualizedFunding": -8.56,
    "oi": 9709810.0,
    "oiUsd": 322171,
    "vol24h": 170938,
    "premium": -0.1654
  },
  {
    "name": "RSR",
    "maxLeverage": 3,
    "mark": 0.001512,
    "prevDay": 0.001544,
    "chg24h": -2.07,
    "funding8h": -0.0032,
    "annualizedFunding": -3.53,
    "oi": 129012278.0,
    "oiUsd": 195067,
    "vol24h": 84646,
    "premium": -0.0661
  },
  {
    "name": "GALA",
    "maxLeverage": 3,
    "mark": 0.003975,
    "prevDay": 0.00388,
    "chg24h": 2.45,
    "funding8h": 0.0013,
    "annualizedFunding": 1.37,
    "oi": 112213052.0,
    "oiUsd": 446047,
    "vol24h": 171811,
    "premium": 0.0
  },
  {
    "name": "JTO",
    "maxLeverage": 5,
    "mark": 0.25802,
    "prevDay": 0.24102,
    "chg24h": 7.05,
    "funding8h": -0.0045,
    "annualizedFunding": -4.9,
    "oi": 4002360.0,
    "oiUsd": 1032689,
    "vol24h": 602820,
    "premium": -0.0986
  },
  {
    "name": "NTRN",
    "maxLeverage": 3,
    "mark": 0.1238,
    "prevDay": 0.12371,
    "chg24h": 0.07,
    "funding8h": 0.0,
    "annualizedFunding": 0.0,
    "oi": 0.0,
    "oiUsd": 0,
    "vol24h": 0,
    "premium": 0.0
  },
  {
    "name": "ACE",
    "maxLeverage": 3,
    "mark": 0.1637,
    "prevDay": 0.1738,
    "chg24h": -5.81,
    "funding8h": -0.013,
    "annualizedFunding": -14.23,
    "oi": 1999414.54,
    "oiUsd": 327304,
    "vol24h": 670099,
    "premium": -0.2438
  },
  {
    "name": "MAV",
    "maxLeverage": 3,
    "mark": 0.016101,
    "prevDay": 0.015979,
    "chg24h": 0.76,
    "funding8h": 0.0013,
    "annualizedFunding": 1.37,
    "oi": 11796280.0,
    "oiUsd": 189932,
    "vol24h": 59039,
    "premium": 0.0
  },
  {
    "name": "WIF",
    "maxLeverage": 5,
    "mark": 0.21521,
    "prevDay": 0.20697,
    "chg24h": 3.98,
    "funding8h": 0.0013,
    "annualizedFunding": 1.37,
    "oi": 24035614.0,
    "oiUsd": 5172704,
    "vol24h": 1567479,
    "premium": 0.0
  },
  {
    "name": "CAKE",
    "maxLeverage": 3,
    "mark": 1.2942,
    "prevDay": 1.3002,
    "chg24h": -0.46,
    "funding8h": -0.0024,
    "annualizedFunding": -2.64,
    "oi": 732117.6,
    "oiUsd": 947507,
    "vol24h": 138472,
    "premium": -0.034
  },
  {
    "name": "PEOPLE",
    "maxLeverage": 3,
    "mark": 0.006637,
    "prevDay": 0.006367,
    "chg24h": 4.24,
    "funding8h": 0.0004,
    "annualizedFunding": 0.41,
    "oi": 23676218.0,
    "oiUsd": 157139,
    "vol24h": 142890,
    "premium": -0.015
  },
  {
    "name": "ENS",
    "maxLeverage": 5,
    "mark": 5.8138,
    "prevDay": 5.5659,
    "chg24h": 4.45,
    "funding8h": -0.0073,
    "annualizedFunding": -7.97,
    "oi": 65672.32,
    "oiUsd": 381806,
    "vol24h": 467725,
    "premium": -0.0876
  },
  {
    "name": "ETC",
    "maxLeverage": 5,
    "mark": 8.2253,
    "prevDay": 8.1373,
    "chg24h": 1.08,
    "funding8h": -0.0034,
    "annualizedFunding": -3.68,
    "oi": 161545.0,
    "oiUsd": 1328756,
    "vol24h": 354330,
    "premium": -0.0461
  },
  {
    "name": "XAI",
    "maxLeverage": 3,
    "mark": 0.01027,
    "prevDay": 0.01036,
    "chg24h": -0.87,
    "funding8h": -0.0043,
    "annualizedFunding": -4.76,
    "oi": 55702667.8,
    "oiUsd": 572066,
    "vol24h": 77941,
    "premium": -0.0972
  },
  {
    "name": "MANTA",
    "maxLeverage": 3,
    "mark": 0.08231,
    "prevDay": 0.07538,
    "chg24h": 9.19,
    "funding8h": -0.0043,
    "annualizedFunding": -4.76,
    "oi": 3181274.2,
    "oiUsd": 261851,
    "vol24h": 354244,
    "premium": -0.0849
  },
  {
    "name": "UMA",
    "maxLeverage": 3,
    "mark": 0.49205,
    "prevDay": 0.48825,
    "chg24h": 0.78,
    "funding8h": -0.002,
    "annualizedFunding": -2.18,
    "oi": 528642.8,
    "oiUsd": 260119,
    "vol24h": 46225,
    "premium": -0.0568
  },
  {
    "name": "ONDO",
    "maxLeverage": 10,
    "mark": 0.25079,
    "prevDay": 0.2415,
    "chg24h": 3.85,
    "funding8h": -0.0005,
    "annualizedFunding": -0.54,
    "oi": 11333860.0,
    "oiUsd": 2842419,
    "vol24h": 891159,
    "premium": -0.0358
  },
  {
    "name": "ALT",
    "maxLeverage": 3,
    "mark": 0.00861,
    "prevDay": 0.008595,
    "chg24h": 0.17,
    "funding8h": 0.0013,
    "annualizedFunding": 1.37,
    "oi": 47953648.0,
    "oiUsd": 412881,
    "vol24h": 279956,
    "premium": 0.0
  },
  {
    "name": "ZETA",
    "maxLeverage": 3,
    "mark": 0.05284,
    "prevDay": 0.05151,
    "chg24h": 2.58,
    "funding8h": -0.0062,
    "annualizedFunding": -6.82,
    "oi": 11506824.0,
    "oiUsd": 608021,
    "vol24h": 169115,
    "premium": -0.1134
  },
  {
    "name": "DYM",
    "maxLeverage": 3,
    "mark": 0.04775,
    "prevDay": 0.05343,
    "chg24h": -10.63,
    "funding8h": -0.0337,
    "annualizedFunding": -36.9,
    "oi": 14647367.8,
    "oiUsd": 699412,
    "vol24h": 1245751,
    "premium": -0.2713
  },
  {
    "name": "MAVIA",
    "maxLeverage": 3,
    "mark": 0.03712,
    "prevDay": 0.03613,
    "chg24h": 2.74,
    "funding8h": 0.0055,
    "annualizedFunding": 5.99,
    "oi": 35768506.8,
    "oiUsd": 1327727,
    "vol24h": 140770,
    "premium": 0.1892
  },
  {
    "name": "W",
    "maxLeverage": 5,
    "mark": 0.01953,
    "prevDay": 0.01897,
    "chg24h": 2.95,
    "funding8h": 0.0013,
    "annualizedFunding": 1.37,
    "oi": 43738995.0,
    "oiUsd": 854223,
    "vol24h": 326445,
    "premium": 0.0
  },
  {
    "name": "PANDORA",
    "maxLeverage": 3,
    "mark": 3026.3,
    "prevDay": 3012.0,
    "chg24h": 0.47,
    "funding8h": 0.0,
    "annualizedFunding": 0.0,
    "oi": 0.0,
    "oiUsd": 0,
    "vol24h": 0,
    "premium": 0.0
  },
  {
    "name": "STRK",
    "maxLeverage": 5,
    "mark": 0.04758,
    "prevDay": 0.04637,
    "chg24h": 2.61,
    "funding8h": -0.0025,
    "annualizedFunding": -2.76,
    "oi": 63104134.6,
    "oiUsd": 3002495,
    "vol24h": 783324,
    "premium": -0.063
  },
  {
    "name": "PIXEL",
    "maxLeverage": 3,
    "mark": 0.024027,
    "prevDay": 0.024008,
    "chg24h": 0.08,
    "funding8h": 0.0,
    "annualizedFunding": 0.0,
    "oi": 0.0,
    "oiUsd": 0,
    "vol24h": 0,
    "premium": 0.0
  },
  {
    "name": "AI",
    "maxLeverage": 3,
    "mark": 0.12555,
    "prevDay": 0.12565,
    "chg24h": -0.08,
    "funding8h": 0.0,
    "annualizedFunding": 0.0,
    "oi": 0.0,
    "oiUsd": 0,
    "vol24h": 0,
    "premium": 0.0
  },
  {
    "name": "TAO",
    "maxLeverage": 5,
    "mark": 154.81,
    "prevDay": 145.65,
    "chg24h": 6.29,
    "funding8h": 0.0013,
    "annualizedFunding": 1.37,
    "oi": 57185.052,
    "oiUsd": 8852818,
    "vol24h": 4782046,
    "premium": -0.0174
  },
  {
    "name": "AR",
    "maxLeverage": 5,
    "mark": 1.9205,
    "prevDay": 1.7615,
    "chg24h": 9.03,
    "funding8h": 0.0013,
    "annualizedFunding": 1.37,
    "oi": 365816.28,
    "oiUsd": 702550,
    "vol24h": 799511,
    "premium": 0.0
  },
  {
    "name": "MYRO",
    "maxLeverage": 3,
    "mark": 0.015813,
    "prevDay": 0.015813,
    "chg24h": 0.0,
    "funding8h": 0.0,
    "annualizedFunding": 0.0,
    "oi": 0.0,
    "oiUsd": 0,
    "vol24h": 0,
    "premium": 0.0
  },
  {
    "name": "kFLOKI",
    "maxLeverage": 5,
    "mark": 0.029928,
    "prevDay": 0.029002,
    "chg24h": 3.19,
    "funding8h": 0.0013,
    "annualizedFunding": 1.37,
    "oi": 15347280.0,
    "oiUsd": 459313,
    "vol24h": 482074,
    "premium": 0.0
  },
  {
    "name": "BOME",
    "maxLeverage": 3,
    "mark": 0.000396,
    "prevDay": 0.00038,
    "chg24h": 4.21,
    "funding8h": 0.0013,
    "annualizedFunding": 1.37,
    "oi": 409134596.0,
    "oiUsd": 162017,
    "vol24h": 65956,
    "premium": 0.0
  },
  {
    "name": "ETHFI",
    "maxLeverage": 5,
    "mark": 0.459,
    "prevDay": 0.4444,
    "chg24h": 3.29,
    "funding8h": 0.0013,
    "annualizedFunding": 1.37,
    "oi": 6707336.4,
    "oiUsd": 3078667,
    "vol24h": 601057,
    "premium": 0.0
  },
  {
    "name": "ENA",
    "maxLeverage": 10,
    "mark": 0.11744,
    "prevDay": 0.11106,
    "chg24h": 5.74,
    "funding8h": 0.0013,
    "annualizedFunding": 1.37,
    "oi": 128409816.0,
    "oiUsd": 15080449,
    "vol24h": 2219051,
    "premium": -0.0111
  },
  {
    "name": "MNT",
    "maxLeverage": 5,
    "mark": 0.61107,
    "prevDay": 0.61676,
    "chg24h": -0.92,
    "funding8h": 0.0013,
    "annualizedFunding": 1.37,
    "oi": 2916623.0,
    "oiUsd": 1782261,
    "vol24h": 384301,
    "premium": -0.0147
  },
  {
    "name": "TNSR",
    "maxLeverage": 3,
    "mark": 0.05615,
    "prevDay": 0.05474,
    "chg24h": 2.58,
    "funding8h": -0.0236,
    "annualizedFunding": -25.81,
    "oi": 9188096.2,
    "oiUsd": 515912,
    "vol24h": 2557992,
    "premium": -0.1066
  },
  {
    "name": "SAGA",
    "maxLeverage": 3,
    "mark": 0.0323,
    "prevDay": 0.03411,
    "chg24h": -5.31,
    "funding8h": 0.0013,
    "annualizedFunding": 1.37,
    "oi": 16831849.4,
    "oiUsd": 543669,
    "vol24h": 449630,
    "premium": -0.0927
  },
  {
    "name": "MERL",
    "maxLeverage": 3,
    "mark": 0.058036,
    "prevDay": 0.049561,
    "chg24h": 17.1,
    "funding8h": 0.0013,
    "annualizedFunding": 1.37,
    "oi": 9092628.0,
    "oiUsd": 527700,
    "vol24h": 512512,
    "premium": 0.0
  },
  {
    "name": "HBAR",
    "maxLeverage": 5,
    "mark": 0.09273,
    "prevDay": 0.088725,
    "chg24h": 4.51,
    "funding8h": 0.0013,
    "annualizedFunding": 1.37,
    "oi": 43962616.0,
    "oiUsd": 4076653,
    "vol24h": 1640199,
    "premium": -0.083
  },
  {
    "name": "POPCAT",
    "maxLeverage": 3,
    "mark": 0.049796,
    "prevDay": 0.048137,
    "chg24h": 3.45,
    "funding8h": 0.0013,
    "annualizedFunding": 1.37,
    "oi": 38095566.0,
    "oiUsd": 1897007,
    "vol24h": 559287,
    "premium": -0.002
  },
  {
    "name": "OMNI",
    "maxLeverage": 3,
    "mark": 4.1915,
    "prevDay": 4.1915,
    "chg24h": 0.0,
    "funding8h": 0.0,
    "annualizedFunding": 0.0,
    "oi": 0.0,
    "oiUsd": 0,
    "vol24h": 0,
    "premium": 0.0
  },
  {
    "name": "EIGEN",
    "maxLeverage": 5,
    "mark": 0.2029,
    "prevDay": 0.1971,
    "chg24h": 2.94,
    "funding8h": -0.0009,
    "annualizedFunding": -0.94,
    "oi": 8774829.64,
    "oiUsd": 1780413,
    "vol24h": 563475,
    "premium": -0.0493
  },
  {
    "name": "REZ",
    "maxLeverage": 3,
    "mark": 0.002976,
    "prevDay": 0.002919,
    "chg24h": 1.95,
    "funding8h": -0.006,
    "annualizedFunding": -6.59,
    "oi": 60690028.0,
    "oiUsd": 180614,
    "vol24h": 83908,
    "premium": -0.0671
  },
  {
    "name": "NOT",
    "maxLeverage": 3,
    "mark": 0.000398,
    "prevDay": 0.000382,
    "chg24h": 4.19,
    "funding8h": 0.0013,
    "annualizedFunding": 1.37,
    "oi": 422638480.0,
    "oiUsd": 168210,
    "vol24h": 32607,
    "premium": -0.2506
  },
  {
    "name": "TURBO",
    "maxLeverage": 3,
    "mark": 0.001049,
    "prevDay": 0.001007,
    "chg24h": 4.17,
    "funding8h": 0.0013,
    "annualizedFunding": 1.37,
    "oi": 306685798.0,
    "oiUsd": 321713,
    "vol24h": 131521,
    "premium": 0.0
  },
  {
    "name": "BRETT",
    "maxLeverage": 3,
    "mark": 0.007142,
    "prevDay": 0.006794,
    "chg24h": 5.12,
    "funding8h": 0.0013,
    "annualizedFunding": 1.37,
    "oi": 103693058.0,
    "oiUsd": 740576,
    "vol24h": 365835,
    "premium": -0.014
  },
  {
    "name": "IO",
    "maxLeverage": 3,
    "mark": 0.1005,
    "prevDay": 0.10016,
    "chg24h": 0.34,
    "funding8h": 0.0013,
    "annualizedFunding": 1.37,
    "oi": 4555921.4,
    "oiUsd": 457870,
    "vol24h": 366114,
    "premium": -0.0695
  },
  {
    "name": "ZK",
    "maxLeverage": 5,
    "mark": 0.022117,
    "prevDay": 0.022102,
    "chg24h": 0.07,
    "funding8h": -0.0094,
    "annualizedFunding": -10.33,
    "oi": 90212320.0,
    "oiUsd": 1995226,
    "vol24h": 612457,
    "premium": -0.0587
  },
  {
    "name": "BLAST",
    "maxLeverage": 3,
    "mark": 0.000565,
    "prevDay": 0.000548,
    "chg24h": 3.1,
    "funding8h": -0.0116,
    "annualizedFunding": -12.71,
    "oi": 1679400094.0,
    "oiUsd": 948861,
    "vol24h": 208053,
    "premium": -0.1764
  },
  {
    "name": "LISTA",
    "maxLeverage": 3,
    "mark": 0.12466,
    "prevDay": 0.12493,
    "chg24h": -0.22,
    "funding8h": 0.0,
    "annualizedFunding": 0.0,
    "oi": 0.0,
    "oiUsd": 0,
    "vol24h": 0,
    "premium": 0.0
  },
  {
    "name": "MEW",
    "maxLeverage": 3,
    "mark": 0.000621,
    "prevDay": 0.000576,
    "chg24h": 7.81,
    "funding8h": -0.008,
    "annualizedFunding": -8.81,
    "oi": 206253722.0,
    "oiUsd": 128084,
    "vol24h": 81929,
    "premium": 0.0
  },
  {
    "name": "RENDER",
    "maxLeverage": 5,
    "mark": 1.3023,
    "prevDay": 1.2694,
    "chg24h": 2.59,
    "funding8h": 0.0003,
    "annualizedFunding": 0.28,
    "oi": 934242.0,
    "oiUsd": 1216663,
    "vol24h": 339431,
    "premium": -0.0644
  },
  {
    "name": "kDOGS",
    "maxLeverage": 3,
    "mark": 0.13659,
    "prevDay": 0.1367,
    "chg24h": -0.08,
    "funding8h": 0.0,
    "annualizedFunding": 0.0,
    "oi": 0.0,
    "oiUsd": 0,
    "vol24h": 0,
    "premium": 0.0
  },
  {
    "name": "POL",
    "maxLeverage": 5,
    "mark": 0.095575,
    "prevDay": 0.088939,
    "chg24h": 7.46,
    "funding8h": 0.0012,
    "annualizedFunding": 1.36,
    "oi": 26211872.0,
    "oiUsd": 2505200,
    "vol24h": 1589242,
    "premium": -0.046
  },
  {
    "name": "CATI",
    "maxLeverage": 3,
    "mark": 0.082821,
    "prevDay": 0.083021,
    "chg24h": -0.24,
    "funding8h": 0.0,
    "annualizedFunding": 0.0,
    "oi": 0.0,
    "oiUsd": 0,
    "vol24h": 0,
    "premium": 0.0
  },
  {
    "name": "CELO",
    "maxLeverage": 3,
    "mark": 0.081062,
    "prevDay": 0.080013,
    "chg24h": 1.31,
    "funding8h": 0.0013,
    "annualizedFunding": 1.37,
    "oi": 7526470.0,
    "oiUsd": 610111,
    "vol24h": 363691,
    "premium": 0.0
  },
  {
    "name": "HMSTR",
    "maxLeverage": 3,
    "mark": 0.000177,
    "prevDay": 0.000176,
    "chg24h": 0.57,
    "funding8h": 0.0013,
    "annualizedFunding": 1.37,
    "oi": 12798751860.0,
    "oiUsd": 2265379,
    "vol24h": 23269,
    "premium": 0.0
  },
  {
    "name": "SCR",
    "maxLeverage": 3,
    "mark": 0.04901,
    "prevDay": 0.04799,
    "chg24h": 2.13,
    "funding8h": -0.0079,
    "annualizedFunding": -8.7,
    "oi": 5014468.2,
    "oiUsd": 245759,
    "vol24h": 272645,
    "premium": -0.0407
  },
  {
    "name": "NEIROETH",
    "maxLeverage": 5,
    "mark": 0.01808,
    "prevDay": 0.018168,
    "chg24h": -0.48,
    "funding8h": 0.0,
    "annualizedFunding": 0.0,
    "oi": 0.0,
    "oiUsd": 0,
    "vol24h": 0,
    "premium": 0.0
  },
  {
    "name": "kNEIRO",
    "maxLeverage": 3,
    "mark": 0.073,
    "prevDay": 0.07077,
    "chg24h": 3.15,
    "funding8h": 0.0013,
    "annualizedFunding": 1.37,
    "oi": 3214899.8,
    "oiUsd": 234688,
    "vol24h": 204143,
    "premium": 0.0
  },
  {
    "name": "GOAT",
    "maxLeverage": 3,
    "mark": 0.023035,
    "prevDay": 0.021591,
    "chg24h": 6.69,
    "funding8h": 0.0013,
    "annualizedFunding": 1.37,
    "oi": 13718552.0,
    "oiUsd": 316007,
    "vol24h": 116696,
    "premium": 0.0
  },
  {
    "name": "MOODENG",
    "maxLeverage": 3,
    "mark": 0.05274,
    "prevDay": 0.042884,
    "chg24h": 22.98,
    "funding8h": -0.105,
    "annualizedFunding": -114.98,
    "oi": 21037532.0,
    "oiUsd": 1109519,
    "vol24h": 3050504,
    "premium": -1.0098
  },
  {
    "name": "GRASS",
    "maxLeverage": 3,
    "mark": 0.19456,
    "prevDay": 0.18774,
    "chg24h": 3.63,
    "funding8h": 0.0013,
    "annualizedFunding": 1.37,
    "oi": 5100888.2,
    "oiUsd": 992429,
    "vol24h": 1296503,
    "premium": 0.0
  },
  {
    "name": "PURR",
    "maxLeverage": 3,
    "mark": 0.070562,
    "prevDay": 0.070459,
    "chg24h": 0.15,
    "funding8h": 0.0013,
    "annualizedFunding": 1.37,
    "oi": 46030306.0,
    "oiUsd": 3247990,
    "vol24h": 375417,
    "premium": 0.0
  },
  {
    "name": "PNUT",
    "maxLeverage": 3,
    "mark": 0.04705,
    "prevDay": 0.04513,
    "chg24h": 4.25,
    "funding8h": -0.0013,
    "annualizedFunding": -1.43,
    "oi": 9765313.0,
    "oiUsd": 459458,
    "vol24h": 430048,
    "premium": 0.0
  },
  {
    "name": "XLM",
    "maxLeverage": 5,
    "mark": 0.15622,
    "prevDay": 0.15415,
    "chg24h": 1.34,
    "funding8h": 0.0003,
    "annualizedFunding": 0.37,
    "oi": 25565530.0,
    "oiUsd": 3993847,
    "vol24h": 1484038,
    "premium": -0.032
  },
  {
    "name": "CHILLGUY",
    "maxLeverage": 3,
    "mark": 0.010053,
    "prevDay": 0.009779,
    "chg24h": 2.8,
    "funding8h": 0.0013,
    "annualizedFunding": 1.37,
    "oi": 41890048.0,
    "oiUsd": 421121,
    "vol24h": 137919,
    "premium": 0.0
  },
  {
    "name": "SAND",
    "maxLeverage": 5,
    "mark": 0.083086,
    "prevDay": 0.08242,
    "chg24h": 0.81,
    "funding8h": -0.0017,
    "annualizedFunding": -1.84,
    "oi": 3154186.0,
    "oiUsd": 262069,
    "vol24h": 680740,
    "premium": -0.0649
  },
  {
    "name": "IOTA",
    "maxLeverage": 3,
    "mark": 0.06685,
    "prevDay": 0.064391,
    "chg24h": 3.82,
    "funding8h": 0.0013,
    "annualizedFunding": 1.37,
    "oi": 4972342.0,
    "oiUsd": 332401,
    "vol24h": 50584,
    "premium": 0.0
  },
  {
    "name": "ALGO",
    "maxLeverage": 5,
    "mark": 0.091285,
    "prevDay": 0.088608,
    "chg24h": 3.02,
    "funding8h": 0.0013,
    "annualizedFunding": 1.37,
    "oi": 8921648.0,
    "oiUsd": 814413,
    "vol24h": 204795,
    "premium": -0.0131
  },
  {
    "name": "HYPE",
    "maxLeverage": 10,
    "mark": 30.66,
    "prevDay": 29.354,
    "chg24h": 4.45,
    "funding8h": 0.0013,
    "annualizedFunding": 1.37,
    "oi": 23678858.04,
    "oiUsd": 725993788,
    "vol24h": 259941503,
    "premium": 0.0
  },
  {
    "name": "ME",
    "maxLeverage": 3,
    "mark": 0.17956,
    "prevDay": 0.1423,
    "chg24h": 26.18,
    "funding8h": -0.3459,
    "annualizedFunding": -378.79,
    "oi": 8631711.6,
    "oiUsd": 1549910,
    "vol24h": 7325825,
    "premium": -2.5939
  },
  {
    "name": "MOVE",
    "maxLeverage": 3,
    "mark": 0.024048,
    "prevDay": 0.022189,
    "chg24h": 8.38,
    "funding8h": -0.1568,
    "annualizedFunding": -171.72,
    "oi": 22522600.0,
    "oiUsd": 541623,
    "vol24h": 2336639,
    "premium": -1.1623
  },
  {
    "name": "VIRTUAL",
    "maxLeverage": 5,
    "mark": 0.58345,
    "prevDay": 0.53799,
    "chg24h": 8.45,
    "funding8h": 0.0005,
    "annualizedFunding": 0.5,
    "oi": 13592188.4,
    "oiUsd": 7930362,
    "vol24h": 4857395,
    "premium": -0.012
  },
  {
    "name": "PENGU",
    "maxLeverage": 5,
    "mark": 0.006254,
    "prevDay": 0.006009,
    "chg24h": 4.08,
    "funding8h": -0.0002,
    "annualizedFunding": -0.19,
    "oi": 371192860.0,
    "oiUsd": 2321440,
    "vol24h": 1894570,
    "premium": -0.032
  },
  {
    "name": "USUAL",
    "maxLeverage": 3,
    "mark": 0.01548,
    "prevDay": 0.01467,
    "chg24h": 5.52,
    "funding8h": 0.0013,
    "annualizedFunding": 1.37,
    "oi": 16333020.6,
    "oiUsd": 252835,
    "vol24h": 66619,
    "premium": 0.0
  },
  {
    "name": "FARTCOIN",
    "maxLeverage": 10,
    "mark": 0.18129,
    "prevDay": 0.1678,
    "chg24h": 8.04,
    "funding8h": 0.0013,
    "annualizedFunding": 1.37,
    "oi": 158131347.8,
    "oiUsd": 28667632,
    "vol24h": 14593566,
    "premium": 0.0
  },
  {
    "name": "AI16Z",
    "maxLeverage": 5,
    "mark": 0.06157,
    "prevDay": 0.06206,
    "chg24h": -0.79,
    "funding8h": 0.0,
    "annualizedFunding": 0.0,
    "oi": 0.0,
    "oiUsd": 0,
    "vol24h": 0,
    "premium": 0.0
  },
  {
    "name": "AIXBT",
    "maxLeverage": 3,
    "mark": 0.02004,
    "prevDay": 0.019013,
    "chg24h": 5.4,
    "funding8h": -0.0076,
    "annualizedFunding": -8.27,
    "oi": 19855456.0,
    "oiUsd": 397903,
    "vol24h": 340094,
    "premium": -0.209
  },
  {
    "name": "ZEREBRO",
    "maxLeverage": 3,
    "mark": 0.007953,
    "prevDay": 0.007824,
    "chg24h": 1.65,
    "funding8h": 0.0013,
    "annualizedFunding": 1.37,
    "oi": 91208642.0,
    "oiUsd": 725382,
    "vol24h": 129017,
    "premium": 0.0
  },
  {
    "name": "BIO",
    "maxLeverage": 3,
    "mark": 0.024195,
    "prevDay": 0.024498,
    "chg24h": -1.24,
    "funding8h": 0.0013,
    "annualizedFunding": 1.37,
    "oi": 12714384.0,
    "oiUsd": 307625,
    "vol24h": 206152,
    "premium": 0.0
  },
  {
    "name": "GRIFFAIN",
    "maxLeverage": 3,
    "mark": 0.009336,
    "prevDay": 0.008967,
    "chg24h": 4.12,
    "funding8h": 0.0013,
    "annualizedFunding": 1.37,
    "oi": 136898376.0,
    "oiUsd": 1278083,
    "vol24h": 232275,
    "premium": 0.0107
  },
  {
    "name": "SPX",
    "maxLeverage": 5,
    "mark": 0.28129,
    "prevDay": 0.28414,
    "chg24h": -1.0,
    "funding8h": 0.0013,
    "annualizedFunding": 1.37,
    "oi": 8821799.6,
    "oiUsd": 2481484,
    "vol24h": 1254738,
    "premium": -0.0461
  },
  {
    "name": "S",
    "maxLeverage": 5,
    "mark": 0.044853,
    "prevDay": 0.044815,
    "chg24h": 0.08,
    "funding8h": 0.0013,
    "annualizedFunding": 1.37,
    "oi": 62037964.0,
    "oiUsd": 2782589,
    "vol24h": 1708393,
    "premium": 0.0
  },
  {
    "name": "MORPHO",
    "maxLeverage": 5,
    "mark": 1.1002,
    "prevDay": 1.0857,
    "chg24h": 1.34,
    "funding8h": 0.0013,
    "annualizedFunding": 1.37,
    "oi": 2528823.8,
    "oiUsd": 2782212,
    "vol24h": 328756,
    "premium": 0.0
  },
  {
    "name": "TRUMP",
    "maxLeverage": 10,
    "mark": 3.2832,
    "prevDay": 3.217,
    "chg24h": 2.06,
    "funding8h": -0.004,
    "annualizedFunding": -4.43,
    "oi": 2008726.2,
    "oiUsd": 6595050,
    "vol24h": 1599654,
    "premium": -0.0815
  },
  {
    "name": "MELANIA",
    "maxLeverage": 3,
    "mark": 0.11746,
    "prevDay": 0.11472,
    "chg24h": 2.39,
    "funding8h": 0.0011,
    "annualizedFunding": 1.22,
    "oi": 10618674.2,
    "oiUsd": 1247269,
    "vol24h": 206785,
    "premium": -0.034
  },
  {
    "name": "ANIME",
    "maxLeverage": 3,
    "mark": 0.005642,
    "prevDay": 0.005499,
    "chg24h": 2.6,
    "funding8h": -0.0012,
    "annualizedFunding": -1.29,
    "oi": 119696344.0,
    "oiUsd": 675327,
    "vol24h": 422157,
    "premium": -0.0708
  },
  {
    "name": "VINE",
    "maxLeverage": 3,
    "mark": 0.018063,
    "prevDay": 0.017879,
    "chg24h": 1.03,
    "funding8h": 0.0013,
    "annualizedFunding": 1.37,
    "oi": 23616586.0,
    "oiUsd": 426586,
    "vol24h": 94207,
    "premium": 0.0
  },
  {
    "name": "VVV",
    "maxLeverage": 3,
    "mark": 1.804,
    "prevDay": 1.8014,
    "chg24h": 0.14,
    "funding8h": 0.0013,
    "annualizedFunding": 1.37,
    "oi": 1072839.24,
    "oiUsd": 1935402,
    "vol24h": 394262,
    "premium": 0.0
  },
  {
    "name": "JELLY",
    "maxLeverage": 3,
    "mark": 0.037555,
    "prevDay": 0.037555,
    "chg24h": 0.0,
    "funding8h": 0.0,
    "annualizedFunding": 0.0,
    "oi": 0.0,
    "oiUsd": 0,
    "vol24h": 0,
    "premium": 0.0
  },
  {
    "name": "BERA",
    "maxLeverage": 5,
    "mark": 0.72923,
    "prevDay": 0.93228,
    "chg24h": -21.78,
    "funding8h": -0.2183,
    "annualizedFunding": -239.09,
    "oi": 9457877.4,
    "oiUsd": 6896968,
    "vol24h": 39732741,
    "premium": -1.7205
  },
  {
    "name": "TST",
    "maxLeverage": 3,
    "mark": 0.010107,
    "prevDay": 0.009751,
    "chg24h": 3.65,
    "funding8h": 0.0013,
    "annualizedFunding": 1.37,
    "oi": 12432646.0,
    "oiUsd": 125657,
    "vol24h": 31822,
    "premium": 0.0198
  },
  {
    "name": "LAYER",
    "maxLeverage": 3,
    "mark": 0.087597,
    "prevDay": 0.084505,
    "chg24h": 3.66,
    "funding8h": 0.0013,
    "annualizedFunding": 1.37,
    "oi": 4239132.0,
    "oiUsd": 371335,
    "vol24h": 253012,
    "premium": 0.0
  },
  {
    "name": "IP",
    "maxLeverage": 3,
    "mark": 1.1325,
    "prevDay": 1.1413,
    "chg24h": -0.77,
    "funding8h": 0.0013,
    "annualizedFunding": 1.37,
    "oi": 5610634.2,
    "oiUsd": 6354043,
    "vol24h": 2071722,
    "premium": 0.0
  },
  {
    "name": "OM",
    "maxLeverage": 3,
    "mark": 0.04593,
    "prevDay": 0.04439,
    "chg24h": 3.47,
    "funding8h": -0.0001,
    "annualizedFunding": -0.08,
    "oi": 16243672.0,
    "oiUsd": 746072,
    "vol24h": 324850,
    "premium": -0.0652
  },
  {
    "name": "KAITO",
    "maxLeverage": 5,
    "mark": 0.3157,
    "prevDay": 0.31659,
    "chg24h": -0.28,
    "funding8h": 0.0013,
    "annualizedFunding": 1.37,
    "oi": 4573144.0,
    "oiUsd": 1443742,
    "vol24h": 591163,
    "premium": 0.0
  },
  {
    "name": "NIL",
    "maxLeverage": 3,
    "mark": 0.05492,
    "prevDay": 0.05203,
    "chg24h": 5.55,
    "funding8h": 0.0013,
    "annualizedFunding": 1.37,
    "oi": 6416308.0,
    "oiUsd": 352384,
    "vol24h": 307574,
    "premium": 0.0
  },
  {
    "name": "PAXG",
    "maxLeverage": 10,
    "mark": 4917.8,
    "prevDay": 5075.8,
    "chg24h": -3.11,
    "funding8h": 0.0013,
    "annualizedFunding": 1.37,
    "oi": 19509.402,
    "oiUsd": 95943337,
    "vol24h": 31900865,
    "premium": 0.0
  },
  {
    "name": "PROMPT",
    "maxLeverage": 3,
    "mark": 0.047186,
    "prevDay": 0.046866,
    "chg24h": 0.68,
    "funding8h": 0.0013,
    "annualizedFunding": 1.37,
    "oi": 40373188.0,
    "oiUsd": 1905049,
    "vol24h": 160584,
    "premium": 0.0
  },
  {
    "name": "BABY",
    "maxLeverage": 3,
    "mark": 0.013484,
    "prevDay": 0.013483,
    "chg24h": 0.01,
    "funding8h": 0.0013,
    "annualizedFunding": 1.37,
    "oi": 15898816.0,
    "oiUsd": 214380,
    "vol24h": 136415,
    "premium": 0.0
  },
  {
    "name": "WCT",
    "maxLeverage": 3,
    "mark": 0.064666,
    "prevDay": 0.065309,
    "chg24h": -0.98,
    "funding8h": 0.0013,
    "annualizedFunding": 1.37,
    "oi": 11246840.0,
    "oiUsd": 727288,
    "vol24h": 339333,
    "premium": 0.0
  },
  {
    "name": "HYPER",
    "maxLeverage": 3,
    "mark": 0.10263,
    "prevDay": 0.095795,
    "chg24h": 7.14,
    "funding8h": -0.0223,
    "annualizedFunding": -24.41,
    "oi": 4464508.0,
    "oiUsd": 458192,
    "vol24h": 180653,
    "premium": -0.1553
  },
  {
    "name": "ZORA",
    "maxLeverage": 3,
    "mark": 0.02094,
    "prevDay": 0.021323,
    "chg24h": -1.8,
    "funding8h": -0.0046,
    "annualizedFunding": -5.04,
    "oi": 55396568.0,
    "oiUsd": 1160004,
    "vol24h": 432382,
    "premium": -0.1191
  },
  {
    "name": "INIT",
    "maxLeverage": 3,
    "mark": 0.070194,
    "prevDay": 0.068191,
    "chg24h": 2.94,
    "funding8h": -0.0181,
    "annualizedFunding": -19.83,
    "oi": 10367376.0,
    "oiUsd": 727728,
    "vol24h": 466888,
    "premium": -0.244
  },
  {
    "name": "DOOD",
    "maxLeverage": 3,
    "mark": 0.003755,
    "prevDay": 0.003513,
    "chg24h": 6.89,
    "funding8h": 0.0013,
    "annualizedFunding": 1.37,
    "oi": 137125886.0,
    "oiUsd": 514908,
    "vol24h": 283395,
    "premium": 0.0
  },
  {
    "name": "LAUNCHCOIN",
    "maxLeverage": 3,
    "mark": 0.060367,
    "prevDay": 0.060054,
    "chg24h": 0.52,
    "funding8h": 0.0,
    "annualizedFunding": 0.0,
    "oi": 0.0,
    "oiUsd": 0,
    "vol24h": 0,
    "premium": 0.0
  },
  {
    "name": "NXPC",
    "maxLeverage": 3,
    "mark": 0.2675,
    "prevDay": 0.25775,
    "chg24h": 3.78,
    "funding8h": -0.0016,
    "annualizedFunding": -1.72,
    "oi": 1570108.0,
    "oiUsd": 420004,
    "vol24h": 154313,
    "premium": -0.0947
  },
  {
    "name": "SOPH",
    "maxLeverage": 3,
    "mark": 0.010022,
    "prevDay": 0.009841,
    "chg24h": 1.84,
    "funding8h": -0.0027,
    "annualizedFunding": -2.9,
    "oi": 47721664.0,
    "oiUsd": 478267,
    "vol24h": 237365,
    "premium": -0.0896
  },
  {
    "name": "RESOLV",
    "maxLeverage": 3,
    "mark": 0.062286,
    "prevDay": 0.063632,
    "chg24h": -2.12,
    "funding8h": -0.0145,
    "annualizedFunding": -15.84,
    "oi": 44663340.0,
    "oiUsd": 2781901,
    "vol24h": 1977479,
    "premium": -0.2082
  },
  {
    "name": "SYRUP",
    "maxLeverage": 3,
    "mark": 0.26668,
    "prevDay": 0.26818,
    "chg24h": -0.56,
    "funding8h": -0.003,
    "annualizedFunding": -3.24,
    "oi": 5641642.0,
    "oiUsd": 1504513,
    "vol24h": 570111,
    "premium": -0.0798
  },
  {
    "name": "PUMP",
    "maxLeverage": 10,
    "mark": 0.001925,
    "prevDay": 0.001846,
    "chg24h": 4.28,
    "funding8h": 0.0013,
    "annualizedFunding": 1.37,
    "oi": 21482286528.0,
    "oiUsd": 41353402,
    "vol24h": 13654432,
    "premium": -0.1038
  },
  {
    "name": "PROVE",
    "maxLeverage": 3,
    "mark": 0.3215,
    "prevDay": 0.31451,
    "chg24h": 2.22,
    "funding8h": 0.0013,
    "annualizedFunding": 1.37,
    "oi": 1441114.0,
    "oiUsd": 463318,
    "vol24h": 152012,
    "premium": 0.0
  },
  {
    "name": "YZY",
    "maxLeverage": 3,
    "mark": 0.33119,
    "prevDay": 0.32898,
    "chg24h": 0.67,
    "funding8h": -0.0166,
    "annualizedFunding": -18.2,
    "oi": 1775508.0,
    "oiUsd": 588030,
    "vol24h": 141995,
    "premium": -0.1673
  },
  {
    "name": "XPL",
    "maxLeverage": 10,
    "mark": 0.090857,
    "prevDay": 0.082811,
    "chg24h": 9.72,
    "funding8h": 0.0013,
    "annualizedFunding": 1.37,
    "oi": 300989724.0,
    "oiUsd": 27347023,
    "vol24h": 19572313,
    "premium": 0.0
  },
  {
    "name": "WLFI",
    "maxLeverage": 5,
    "mark": 0.10748,
    "prevDay": 0.10305,
    "chg24h": 4.3,
    "funding8h": -0.0068,
    "annualizedFunding": -7.42,
    "oi": 120203908.0,
    "oiUsd": 12919516,
    "vol24h": 3853303,
    "premium": -0.1013
  },
  {
    "name": "LINEA",
    "maxLeverage": 3,
    "mark": 0.003637,
    "prevDay": 0.003586,
    "chg24h": 1.42,
    "funding8h": -0.0004,
    "annualizedFunding": -0.4,
    "oi": 507373838.0,
    "oiUsd": 1845319,
    "vol24h": 2843513,
    "premium": -0.1098
  },
  {
    "name": "SKY",
    "maxLeverage": 3,
    "mark": 0.066608,
    "prevDay": 0.065547,
    "chg24h": 1.62,
    "funding8h": 0.0013,
    "annualizedFunding": 1.37,
    "oi": 32142386.0,
    "oiUsd": 2140940,
    "vol24h": 408845,
    "premium": -0.033
  },
  {
    "name": "ASTER",
    "maxLeverage": 5,
    "mark": 0.71229,
    "prevDay": 0.68828,
    "chg24h": 3.49,
    "funding8h": 0.0013,
    "annualizedFunding": 1.37,
    "oi": 72318302.0,
    "oiUsd": 51511603,
    "vol24h": 31067790,
    "premium": -0.0112
  },
  {
    "name": "AVNT",
    "maxLeverage": 5,
    "mark": 0.19792,
    "prevDay": 0.18537,
    "chg24h": 6.77,
    "funding8h": -0.0315,
    "annualizedFunding": -34.48,
    "oi": 7548714.0,
    "oiUsd": 1494041,
    "vol24h": 1659976,
    "premium": -0.34
  },
  {
    "name": "STBL",
    "maxLeverage": 3,
    "mark": 0.04135,
    "prevDay": 0.040237,
    "chg24h": 2.77,
    "funding8h": 0.0013,
    "annualizedFunding": 1.37,
    "oi": 70167286.0,
    "oiUsd": 2901417,
    "vol24h": 1156996,
    "premium": 0.0048
  },
  {
    "name": "0G",
    "maxLeverage": 3,
    "mark": 0.63769,
    "prevDay": 0.55533,
    "chg24h": 14.83,
    "funding8h": -0.1649,
    "annualizedFunding": -180.51,
    "oi": 1827792.0,
    "oiUsd": 1165565,
    "vol24h": 5620389,
    "premium": -1.294
  },
  {
    "name": "HEMI",
    "maxLeverage": 3,
    "mark": 0.010642,
    "prevDay": 0.011343,
    "chg24h": -6.18,
    "funding8h": 0.0013,
    "annualizedFunding": 1.37,
    "oi": 145971998.0,
    "oiUsd": 1553434,
    "vol24h": 134356,
    "premium": 0.0
  },
  {
    "name": "APEX",
    "maxLeverage": 3,
    "mark": 0.28035,
    "prevDay": 0.29269,
    "chg24h": -4.22,
    "funding8h": 0.0013,
    "annualizedFunding": 1.37,
    "oi": 2784522.0,
    "oiUsd": 780641,
    "vol24h": 648951,
    "premium": 0.0
  },
  {
    "name": "2Z",
    "maxLeverage": 3,
    "mark": 0.078805,
    "prevDay": 0.07498,
    "chg24h": 5.1,
    "funding8h": 0.0013,
    "annualizedFunding": 1.37,
    "oi": 20831688.0,
    "oiUsd": 1641641,
    "vol24h": 490983,
    "premium": -0.0481
  },
  {
    "name": "ZEC",
    "maxLeverage": 10,
    "mark": 232.26,
    "prevDay": 238.56,
    "chg24h": -2.64,
    "funding8h": -0.0003,
    "annualizedFunding": -0.34,
    "oi": 240773.58,
    "oiUsd": 55922072,
    "vol24h": 39088951,
    "premium": -0.0381
  },
  {
    "name": "MON",
    "maxLeverage": 5,
    "mark": 0.020096,
    "prevDay": 0.019167,
    "chg24h": 4.85,
    "funding8h": 0.0013,
    "annualizedFunding": 1.37,
    "oi": 1373221222.0,
    "oiUsd": 27596254,
    "vol24h": 4107460,
    "premium": 0.0
  },
  {
    "name": "MET",
    "maxLeverage": 3,
    "mark": 0.21052,
    "prevDay": 0.20921,
    "chg24h": 0.63,
    "funding8h": 0.0013,
    "annualizedFunding": 1.37,
    "oi": 10843194.0,
    "oiUsd": 2282709,
    "vol24h": 341606,
    "premium": -0.0484
  },
  {
    "name": "MEGA",
    "maxLeverage": 3,
    "mark": 0.12496,
    "prevDay": 0.11986,
    "chg24h": 4.25,
    "funding8h": 0.0013,
    "annualizedFunding": 1.37,
    "oi": 30768004.0,
    "oiUsd": 3844770,
    "vol24h": 406139,
    "premium": -0.0057
  },
  {
    "name": "CC",
    "maxLeverage": 3,
    "mark": 0.16505,
    "prevDay": 0.16243,
    "chg24h": 1.61,
    "funding8h": 0.0018,
    "annualizedFunding": 2.0,
    "oi": 37787078.0,
    "oiUsd": 6236757,
    "vol24h": 996971,
    "premium": 0.0777
  },
  {
    "name": "ICP",
    "maxLeverage": 5,
    "mark": 2.3466,
    "prevDay": 2.3389,
    "chg24h": 0.33,
    "funding8h": 0.0013,
    "annualizedFunding": 1.37,
    "oi": 429937.6,
    "oiUsd": 1008892,
    "vol24h": 1657959,
    "premium": -0.0166
  },
  {
    "name": "AERO",
    "maxLeverage": 3,
    "mark": 0.29667,
    "prevDay": 0.27927,
    "chg24h": 6.23,
    "funding8h": -0.0023,
    "annualizedFunding": -2.49,
    "oi": 5018310.0,
    "oiUsd": 1488782,
    "vol24h": 923210,
    "premium": -0.0205
  },
  {
    "name": "STABLE",
    "maxLeverage": 3,
    "mark": 0.02346,
    "prevDay": 0.022476,
    "chg24h": 4.38,
    "funding8h": -0.0136,
    "annualizedFunding": -14.93,
    "oi": 95982574.0,
    "oiUsd": 2251751,
    "vol24h": 940681,
    "premium": -0.1999
  },
  {
    "name": "FOGO",
    "maxLeverage": 3,
    "mark": 0.020998,
    "prevDay": 0.020316,
    "chg24h": 3.36,
    "funding8h": 0.0013,
    "annualizedFunding": 1.37,
    "oi": 29658678.0,
    "oiUsd": 622773,
    "vol24h": 175564,
    "premium": -0.0048
  },
  {
    "name": "LIT",
    "maxLeverage": 5,
    "mark": 1.4147,
    "prevDay": 1.4008,
    "chg24h": 0.99,
    "funding8h": 0.0013,
    "annualizedFunding": 1.37,
    "oi": 31180810.0,
    "oiUsd": 44111492,
    "vol24h": 15765480,
    "premium": 0.0424
  },
  {
    "name": "XMR",
    "maxLeverage": 5,
    "mark": 334.25,
    "prevDay": 345.3,
    "chg24h": -3.2,
    "funding8h": 0.0017,
    "annualizedFunding": 1.9,
    "oi": 72633.418,
    "oiUsd": 24277720,
    "vol24h": 4635193,
    "premium": 0.1006
  },
  {
    "name": "AXS",
    "maxLeverage": 5,
    "mark": 1.4046,
    "prevDay": 1.4951,
    "chg24h": -6.05,
    "funding8h": -0.0837,
    "annualizedFunding": -91.69,
    "oi": 1816890.8,
    "oiUsd": 2552005,
    "vol24h": 1981515,
    "premium": -0.7591
  },
  {
    "name": "DASH",
    "maxLeverage": 5,
    "mark": 34.171,
    "prevDay": 33.837,
    "chg24h": 0.99,
    "funding8h": 0.0013,
    "annualizedFunding": 1.37,
    "oi": 286621.56,
    "oiUsd": 9794145,
    "vol24h": 666133,
    "premium": 0.0
  },
  {
    "name": "SKR",
    "maxLeverage": 3,
    "mark": 0.023425,
    "prevDay": 0.025798,
    "chg24h": -9.2,
    "funding8h": -0.003,
    "annualizedFunding": -3.28,
    "oi": 57492120.0,
    "oiUsd": 1346753,
    "vol24h": 2081405,
    "premium": -0.162
  },
  {
    "name": "AZTEC",
    "maxLeverage": 3,
    "mark": 0.020665,
    "prevDay": 0.020201,
    "chg24h": 2.3,
    "funding8h": 0.0013,
    "annualizedFunding": 1.37,
    "oi": 69282208.0,
    "oiUsd": 1431717,
    "vol24h": 5222279,
    "premium": 0.0
  }
]